LICENSE
MANIFEST.in
README.txt
setup.py
django_hookbox.egg-info/PKG-INFO
django_hookbox.egg-info/SOURCES.txt
django_hookbox.egg-info/dependency_links.txt
django_hookbox.egg-info/requires.txt
django_hookbox.egg-info/top_level.txt
djhookbox/__init__.py
djhookbox/models.py
djhookbox/tests.py
djhookbox/urls.py
djhookbox/views.py
djhookbox/management/__init__.py
djhookbox/management/commands/__init__.py
djhookbox/management/commands/runhookbox.py