Metadata-Version: 1.0
Name: django-hookbox
Version: 0.3
Summary: Integrate hookbox with Django.
Home-page: https://github.com/duaneg/django-hookbox
Author: Duane Griffin
Author-email: duaneg@dghda.com
License: BSD
Platform: UNKNOWN
Classifier: Development Status :: 3 - Alpha
Classifier: Environment :: Web Environment
Classifier: Framework :: Django
Classifier: Intended Audience :: Developers
Classifier: License :: OSI Approved :: BSD License
Classifier: Operating System :: OS Independent
Classifier: Programming Language :: Python
Classifier: Topic :: Internet :: WWW/HTTP
Classifier: Topic :: Utilities
